<?xml version="1.0" encoding="UTF-8"?>

<!-- generated on 2023-04-29 01:23:18 by Eclipse SUMO GUI Version 1.16.0
<configuration xmlns:xsi="http://www.w3.org/2001/XMLSchema-instance" xsi:noNamespaceSchemaLocation="http://sumo.dlr.de/xsd/sumoConfiguration.xsd">

    <input>
        <net-file value="../../../nets/berlin/berlin.net.xml"/>
        <route-files value="../../../nets/berlin/berlin.rou.xml"/>
    </input>

    <output>
        <battery-output value="../../../nets/berlin/battery.xml"/>
        <chargingstations-output value="../../../nets/berlin/chargingstations.xml"/>
        <summary-output value="../../../nets/berlin/results.out.xml"/>
    </output>

    <processing>
        <collision.check-junctions value="True"/>
        <time-to-teleport value="-1"/>
        <waiting-time-memory value="1000"/>
        <max-depart-delay value="-1"/>
        <lanechange.overtake-right value="False"/>
    </processing>

    <report>
        <verbose value="true"/>
        <duration-log.statistics value="true"/>
    </report>

    <traci_server>
        <remote-port value="60841"/>
    </traci_server>

    <random_number>
        <random value="true"/>
    </random_number>

    <gui_only>
        <quit-on-end value="true"/>
        <start value="true"/>
    </gui_only>

</configuration>
-->

<summary xmlns:xsi="http://www.w3.org/2001/XMLSchema-instance" xsi:noNamespaceSchemaLocation="http://sumo.dlr.de/xsd/summary_file.xsd">
    <step time="0.00" loaded="14" inserted="7" running="7" waiting="7" ended="0" arrived="0" collisions="0" teleports="0" halting="0" stopped="0" meanWaitingTime="0.00" meanTravelTime="-1.00" meanSpeed="11.60" meanSpeedRelative="0.95" duration="1682727799844"/>
    <step time="1.00" loaded="16" inserted="14" running="14" waiting="0" ended="2" arrived="0" collisions="0" teleports="0" halting="0" stopped="0" meanWaitingTime="0.50" meanTravelTime="0.00" meanSpeed="10.16" meanSpeedRelative="0.82" duration="1682727799990"/>
    <step time="2.00" loaded="16" inserted="14" running="14" waiting="0" ended="2" arrived="0" collisions="0" teleports="0" halting="0" stopped="0" meanWaitingTime="0.50" meanTravelTime="0.00" meanSpeed="9.91" meanSpeedRelative="0.80" duration="1682727800014"/>
    <step time="3.00" loaded="16" inserted="14" running="14" waiting="0" ended="2" arrived="0" collisions="0" teleports="0" halting="0" stopped="0" meanWaitingTime="0.50" meanTravelTime="0.00" meanSpeed="10.38" meanSpeedRelative="0.85" duration="1682727800040"/>
    <step time="4.00" loaded="18" inserted="14" running="14" waiting="0" ended="4" arrived="0" collisions="0" teleports="0" halting="0" stopped="0" meanWaitingTime="0.50" meanTravelTime="0.00" meanSpeed="10.05" meanSpeedRelative="0.82" duration="1682727800066"/>
    <step time="5.00" loaded="18" inserted="14" running="14" waiting="0" ended="4" arrived="0" collisions="0" teleports="0" halting="0" stopped="0" meanWaitingTime="0.50" meanTravelTime="0.00" meanSpeed="10.25" meanSpeedRelative="0.84" duration="1682727800092"/>
    <step time="6.00" loaded="18" inserted="14" running="14" waiting="0" ended="4" arrived="0" collisions="0" teleports="0" halting="0" stopped="0" meanWaitingTime="0.50" meanTravelTime="0.00" meanSpeed="10.11" meanSpeedRelative="0.82" duration="1682727800112"/>
    <step time="7.00" loaded="18" inserted="14" running="14" waiting="0" ended="4" arrived="0" collisions="0" teleports="0" halting="0" stopped="0" meanWaitingTime="0.50" meanTravelTime="0.00" meanSpeed="9.74" meanSpeedRelative="0.79" duration="1682727800135"/>
    <step time="8.00" loaded="18" inserted="14" running="14" waiting="0" ended="4" arrived="0" collisions="0" teleports="0" halting="0" stopped="0" meanWaitingTime="0.50" meanTravelTime="0.00" meanSpeed="9.46" meanSpeedRelative="0.76" duration="1682727800156"/>
    <step time="9.00" loaded="20" inserted="14" running="14" waiting="0" ended="6" arrived="0" collisions="0" teleports="0" halting="0" stopped="0" meanWaitingTime="0.50" meanTravelTime="0.00" meanSpeed="9.35" meanSpeedRelative="0.75" duration="1682727800180"/>
    <step time="10.00" loaded="20" inserted="14" running="14" waiting="0" ended="6" arrived="0" collisions="0" teleports="0" halting="0" stopped="0" meanWaitingTime="0.50" meanTravelTime="0.00" meanSpeed="9.54" meanSpeedRelative="0.77" duration="1682727800203"/>
    <step time="11.00" loaded="20" inserted="14" running="14" waiting="0" ended="6" arrived="0" collisions="0" teleports="0" halting="0" stopped="0" meanWaitingTime="0.50" meanTravelTime="0.00" meanSpeed="9.68" meanSpeedRelative="0.79" duration="1682727800225"/>
    <step time="12.00" loaded="20" inserted="14" running="14" waiting="0" ended="6" arrived="0" collisions="0" teleports="0" halting="0" stopped="0" meanWaitingTime="0.50" meanTravelTime="0.00" meanSpeed="9.70" meanSpeedRelative="0.80" duration="1682727800247"/>
    <step time="13.00" loaded="20" inserted="14" running="14" waiting="0" ended="6" arrived="0" collisions="0" teleports="0" halting="0" stopped="0" meanWaitingTime="0.50" meanTravelTime="0.00" meanSpeed="9.73" meanSpeedRelative="0.81" duration="1682727800270"/>
    <step time="14.00" loaded="20" inserted="14" running="14" waiting="0" ended="6" arrived="0" collisions="0" teleports="0" halting="0" stopped="0" meanWaitingTime="0.50" meanTravelTime="0.00" meanSpeed="9.43" meanSpeedRelative="0.78" duration="1682727800292"/>
    <step time="15.00" loaded="20" inserted="14" running="14" waiting="0" ended="6" arrived="0" collisions="0" teleports="0" halting="0" stopped="0" meanWaitingTime="0.50" meanTravelTime="0.00" meanSpeed="9.17" meanSpeedRelative="0.77" duration="1682727800315"/>
    <step time="16.00" loaded="20" inserted="14" running="14" waiting="0" ended="6" arrived="0" collisions="0" teleports="0" halting="0" stopped="0" meanWaitingTime="0.50" meanTravelTime="0.00" meanSpeed="8.75" meanSpeedRelative="0.76" duration="1682727800338"/>
    <step time="17.00" loaded="20" inserted="14" running="14" waiting="0" ended="6" arrived="0" collisions="0" teleports="0" halting="0" stopped="0" meanWaitingTime="0.50" meanTravelTime="0.00" meanSpeed="8.50" meanSpeedRelative="0.74" duration="1682727800360"/>
    <step time="18.00" loaded="20" inserted="14" running="14" waiting="0" ended="6" arrived="0" collisions="0" teleports="0" halting="0" stopped="0" meanWaitingTime="0.50" meanTravelTime="0.00" meanSpeed="8.64" meanSpeedRelative="0.75" duration="1682727800383"/>
    <step time="19.00" loaded="20" inserted="14" running="14" waiting="0" ended="6" arrived="0" collisions="0" teleports="0" halting="0" stopped="0" meanWaitingTime="0.50" meanTravelTime="0.00" meanSpeed="8.67" meanSpeedRelative="0.72" duration="1682727800406"/>
    <step time="20.00" loaded="20" inserted="14" running="14" waiting="0" ended="6" arrived="0" collisions="0" teleports="0" halting="0" stopped="0" meanWaitingTime="0.50" meanTravelTime="0.00" meanSpeed="8.18" meanSpeedRelative="0.68" duration="1682727800431"/>
    <step time="21.00" loaded="20" inserted="14" running="14" waiting="0" ended="6" arrived="0" collisions="0" teleports="0" halting="0" stopped="0" meanWaitingTime="0.50" meanTravelTime="0.00" meanSpeed="8.45" meanSpeedRelative="0.70" duration="1682727800453"/>
    <step time="22.00" loaded="20" inserted="14" running="14" waiting="0" ended="6" arrived="0" collisions="0" teleports="0" halting="0" stopped="0" meanWaitingTime="0.50" meanTravelTime="0.00" meanSpeed="8.57" meanSpeedRelative="0.71" duration="1682727800477"/>
    <step time="23.00" loaded="22" inserted="14" running="14" waiting="0" ended="8" arrived="0" collisions="0" teleports="0" halting="0" stopped="0" meanWaitingTime="0.50" meanTravelTime="0.00" meanSpeed="8.60" meanSpeedRelative="0.72" duration="1682727800504"/>
    <step time="24.00" loaded="22" inserted="14" running="14" waiting="0" ended="8" arrived="0" collisions="0" teleports="0" halting="0" stopped="0" meanWaitingTime="0.50" meanTravelTime="0.00" meanSpeed="8.36" meanSpeedRelative="0.70" duration="1682727800529"/>
    <step time="25.00" loaded="22" inserted="14" running="14" waiting="0" ended="8" arrived="0" collisions="0" teleports="0" halting="0" stopped="0" meanWaitingTime="0.50" meanTravelTime="0.00" meanSpeed="8.03" meanSpeedRelative="0.71" duration="1682727800553"/>
    <step time="26.00" loaded="22" inserted="14" running="14" waiting="0" ended="8" arrived="0" collisions="0" teleports="0" halting="0" stopped="0" meanWaitingTime="0.50" meanTravelTime="0.00" meanSpeed="7.66" meanSpeedRelative="0.71" duration="1682727800578"/>
    <step time="27.00" loaded="22" inserted="14" running="14" waiting="0" ended="8" arrived="0" collisions="0" teleports="0" halting="0" stopped="0" meanWaitingTime="0.50" meanTravelTime="0.00" meanSpeed="7.79" meanSpeedRelative="0.71" duration="1682727800602"/>
    <step time="28.00" loaded="22" inserted="14" running="14" waiting="0" ended="8" arrived="0" collisions="0" teleports="0" halting="0" stopped="0" meanWaitingTime="0.50" meanTravelTime="0.00" meanSpeed="7.87" meanSpeedRelative="0.74" duration="1682727800628"/>
    <step time="29.00" loaded="22" inserted="14" running="14" waiting="0" ended="8" arrived="0" collisions="0" teleports="0" halting="0" stopped="0" meanWaitingTime="0.50" meanTravelTime="0.00" meanSpeed="7.67" meanSpeedRelative="0.72" duration="1682727800655"/>
    <step time="30.00" loaded="29" inserted="21" running="21" waiting="0" ended="8" arrived="0" collisions="0" teleports="0" halting="0" stopped="0" meanWaitingTime="0.33" meanTravelTime="0.00" meanSpeed="9.13" meanSpeedRelative="0.80" duration="1682727800678"/>
    <step time="31.00" loaded="29" inserted="21" running="21" waiting="0" ended="8" arrived="0" collisions="0" teleports="0" halting="0" stopped="0" meanWaitingTime="0.33" meanTravelTime="0.00" meanSpeed="9.22" meanSpeedRelative="0.85" duration="1682727800711"/>
    <step time="32.00" loaded="29" inserted="21" running="21" waiting="0" ended="8" arrived="0" collisions="0" teleports="0" halting="0" stopped="0" meanWaitingTime="0.33" meanTravelTime="0.00" meanSpeed="9.05" meanSpeedRelative="0.90" duration="1682727800738"/>
    <step time="33.00" loaded="29" inserted="21" running="21" waiting="0" ended="8" arrived="0" collisions="0" teleports="0" halting="0" stopped="0" meanWaitingTime="0.33" meanTravelTime="0.00" meanSpeed="8.88" meanSpeedRelative="0.85" duration="1682727800768"/>
    <step time="34.00" loaded="31" inserted="21" running="21" waiting="0" ended="10" arrived="0" collisions="0" teleports="0" halting="0" stopped="0" meanWaitingTime="0.33" meanTravelTime="0.00" meanSpeed="8.75" meanSpeedRelative="0.84" duration="1682727800800"/>
    <step time="35.00" loaded="31" inserted="21" running="21" waiting="0" ended="10" arrived="0" collisions="0" teleports="0" halting="0" stopped="0" meanWaitingTime="0.33" meanTravelTime="0.00" meanSpeed="8.52" meanSpeedRelative="0.82" duration="1682727800828"/>
    <step time="36.00" loaded="31" inserted="21" running="21" waiting="0" ended="10" arrived="0" collisions="0" teleports="0" halting="0" stopped="0" meanWaitingTime="0.33" meanTravelTime="0.00" meanSpeed="8.53" meanSpeedRelative="0.85" duration="1682727800856"/>
    <step time="37.00" loaded="31" inserted="21" running="21" waiting="0" ended="10" arrived="0" collisions="0" teleports="0" halting="0" stopped="0" meanWaitingTime="0.33" meanTravelTime="0.00" meanSpeed="8.40" meanSpeedRelative="0.86" duration="1682727800997"/>
    <step time="38.00" loaded="31" inserted="21" running="21" waiting="0" ended="10" arrived="0" collisions="0" teleports="0" halting="0" stopped="0" meanWaitingTime="0.33" meanTravelTime="0.00" meanSpeed="7.99" meanSpeedRelative="0.82" duration="1682727801027"/>
    <step time="39.00" loaded="33" inserted="21" running="21" waiting="0" ended="12" arrived="0" collisions="0" teleports="0" halting="0" stopped="0" meanWaitingTime="0.33" meanTravelTime="0.00" meanSpeed="8.05" meanSpeedRelative="0.81" duration="1682727801058"/>
    <step time="40.00" loaded="33" inserted="21" running="21" waiting="0" ended="12" arrived="0" collisions="0" teleports="0" halting="0" stopped="0" meanWaitingTime="0.33" meanTravelTime="0.00" meanSpeed="7.90" meanSpeedRelative="0.80" duration="1682727801088"/>
    <step time="41.00" loaded="33" inserted="21" running="21" waiting="0" ended="12" arrived="0" collisions="0" teleports="0" halting="0" stopped="0" meanWaitingTime="0.33" meanTravelTime="0.00" meanSpeed="7.87" meanSpeedRelative="0.80" duration="1682727801117"/>
    <step time="42.00" loaded="33" inserted="21" running="21" waiting="0" ended="12" arrived="0" collisions="0" teleports="0" halting="0" stopped="0" meanWaitingTime="0.33" meanTravelTime="0.00" meanSpeed="7.74" meanSpeedRelative="0.79" duration="1682727801146"/>
    <step time="43.00" loaded="33" inserted="21" running="21" waiting="0" ended="12" arrived="0" collisions="0" teleports="0" halting="0" stopped="0" meanWaitingTime="0.33" meanTravelTime="0.00" meanSpeed="7.74" meanSpeedRelative="0.79" duration="1682727801174"/>
    <step time="44.00" loaded="33" inserted="21" running="21" waiting="0" ended="12" arrived="0" collisions="0" teleports="0" halting="0" stopped="0" meanWaitingTime="0.33" meanTravelTime="0.00" meanSpeed="7.58" meanSpeedRelative="0.78" duration="1682727801205"/>
    <step time="45.00" loaded="33" inserted="21" running="21" waiting="0" ended="12" arrived="0" collisions="0" teleports="0" halting="0" stopped="0" meanWaitingTime="0.33" meanTravelTime="0.00" meanSpeed="7.22" meanSpeedRelative="0.82" duration="1682727801233"/>
    <step time="46.00" loaded="33" inserted="21" running="21" waiting="0" ended="12" arrived="0" collisions="0" teleports="0" halting="0" stopped="0" meanWaitingTime="0.33" meanTravelTime="0.00" meanSpeed="6.89" meanSpeedRelative="0.77" duration="1682727801263"/>
    <step time="47.00" loaded="33" inserted="21" running="21" waiting="0" ended="12" arrived="0" collisions="0" teleports="0" halting="0" stopped="0" meanWaitingTime="0.33" meanTravelTime="0.00" meanSpeed="6.54" meanSpeedRelative="0.73" duration="1682727801292"/>
    <step time="48.00" loaded="35" inserted="21" running="21" waiting="0" ended="14" arrived="0" collisions="0" teleports="0" halting="0" stopped="0" meanWaitingTime="0.33" meanTravelTime="0.00" meanSpeed="6.63" meanSpeedRelative="0.72" duration="1682727801326"/>
    <step time="49.00" loaded="35" inserted="21" running="21" waiting="0" ended="14" arrived="0" collisions="0" teleports="0" halting="0" stopped="0" meanWaitingTime="0.33" meanTravelTime="0.00" meanSpeed="6.82" meanSpeedRelative="0.72" duration="1682727801358"/>
    <step time="50.00" loaded="35" inserted="21" running="21" waiting="0" ended="14" arrived="0" collisions="0" teleports="0" halting="0" stopped="0" meanWaitingTime="0.33" meanTravelTime="0.00" meanSpeed="7.31" meanSpeedRelative="0.83" duration="1682727801390"/>
    <step time="51.00" loaded="35" inserted="21" running="21" waiting="0" ended="14" arrived="0" collisions="0" teleports="0" halting="0" stopped="0" meanWaitingTime="0.33" meanTravelTime="0.00" meanSpeed="7.61" meanSpeedRelative="0.85" duration="1682727801424"/>
    <step time="52.00" loaded="35" inserted="21" running="21" waiting="0" ended="14" arrived="0" collisions="0" teleports="0" halting="0" stopped="0" meanWaitingTime="0.33" meanTravelTime="0.00" meanSpeed="7.85" meanSpeedRelative="0.88" duration="1682727801458"/>
    <step time="53.00" loaded="35" inserted="21" running="21" waiting="0" ended="14" arrived="0" collisions="0" teleports="0" halting="0" stopped="0" meanWaitingTime="0.33" meanTravelTime="0.00" meanSpeed="7.92" meanSpeedRelative="0.89" duration="1682727801495"/>
    <step time="54.00" loaded="35" inserted="21" running="21" waiting="0" ended="14" arrived="0" collisions="0" teleports="0" halting="0" stopped="0" meanWaitingTime="0.33" meanTravelTime="0.00" meanSpeed="7.87" meanSpeedRelative="0.88" duration="1682727801532"/>
    <step time="55.00" loaded="37" inserted="21" running="21" waiting="0" ended="16" arrived="0" collisions="0" teleports="0" halting="0" stopped="0" meanWaitingTime="0.33" meanTravelTime="0.00" meanSpeed="7.75" meanSpeedRelative="0.87" duration="1682727801571"/>
    <step time="56.00" loaded="37" inserted="21" running="21" waiting="0" ended="16" arrived="0" collisions="0" teleports="0" halting="0" stopped="0" meanWaitingTime="0.33" meanTravelTime="0.00" meanSpeed="7.78" meanSpeedRelative="0.87" duration="1682727801607"/>
    <step time="57.00" loaded="37" inserted="21" running="21" waiting="0" ended="16" arrived="0" collisions="0" teleports="0" halting="0" stopped="0" meanWaitingTime="0.33" meanTravelTime="0.00" meanSpeed="7.82" meanSpeedRelative="0.87" duration="1682727801644"/>
    <step time="58.00" loaded="37" inserted="21" running="21" waiting="0" ended="16" arrived="0" collisions="0" teleports="0" halting="0" stopped="0" meanWaitingTime="0.33" meanTravelTime="0.00" meanSpeed="7.79" meanSpeedRelative="0.87" duration="1682727801680"/>
    <step time="59.00" loaded="37" inserted="21" running="21" waiting="0" ended="16" arrived="0" collisions="0" teleports="0" halting="0" stopped="0" meanWaitingTime="0.33" meanTravelTime="0.00" meanSpeed="7.40" meanSpeedRelative="0.83" duration="1682727801716"/>
    <step time="60.00" loaded="44" inserted="28" running="28" waiting="0" ended="16" arrived="0" collisions="0" teleports="0" halting="0" stopped="0" meanWaitingTime="0.25" meanTravelTime="0.00" meanSpeed="8.65" meanSpeedRelative="0.87" duration="1682727801752"/>
    <step time="61.00" loaded="46" inserted="28" running="28" waiting="0" ended="18" arrived="0" collisions="0" teleports="0" halting="0" stopped="0" meanWaitingTime="0.25" meanTravelTime="0.00" meanSpeed="8.68" meanSpeedRelative="0.90" duration="1682727801799"/>
    <step time="62.00" loaded="46" inserted="28" running="28" waiting="0" ended="18" arrived="0" collisions="0" teleports="0" halting="0" stopped="0" meanWaitingTime="0.25" meanTravelTime="0.00" meanSpeed="8.51" meanSpeedRelative="0.87" duration="1682727801840"/>
    <step time="63.00" loaded="46" inserted="28" running="28" waiting="0" ended="18" arrived="0" collisions="0" teleports="0" halting="0" stopped="0" meanWaitingTime="0.25" meanTravelTime="0.00" meanSpeed="8.56" meanSpeedRelative="0.87" duration="1682727801883"/>
    <step time="64.00" loaded="48" inserted="28" running="28" waiting="0" ended="20" arrived="0" collisions="0" teleports="0" halting="0" stopped="0" meanWaitingTime="0.25" meanTravelTime="0.00" meanSpeed="8.51" meanSpeedRelative="0.87" duration="1682727802034"/>
    <step time="65.00" loaded="48" inserted="28" running="28" waiting="0" ended="20" arrived="0" collisions="0" teleports="0" halting="0" stopped="0" meanWaitingTime="0.25" meanTravelTime="0.00" meanSpeed="8.45" meanSpeedRelative="0.86" duration="1682727802074"/>
    <step time="66.00" loaded="48" inserted="28" running="28" waiting="0" ended="20" arrived="0" collisions="0" teleports="0" halting="0" stopped="0" meanWaitingTime="0.25" meanTravelTime="0.00" meanSpeed="8.33" meanSpeedRelative="0.88" duration="1682727802113"/>
    <step time="67.00" loaded="50" inserted="28" running="28" waiting="0" ended="22" arrived="0" collisions="0" teleports="0" halting="0" stopped="0" meanWaitingTime="0.25" meanTravelTime="0.00" meanSpeed="8.15" meanSpeedRelative="0.86" duration="1682727802156"/>
    <step time="68.00" loaded="50" inserted="28" running="28" waiting="0" ended="22" arrived="0" collisions="0" teleports="0" halting="0" stopped="0" meanWaitingTime="0.25" meanTravelTime="0.00" meanSpeed="8.04" meanSpeedRelative="0.85" duration="1682727802196"/>
    <step time="69.00" loaded="50" inserted="28" running="28" waiting="0" ended="22" arrived="0" collisions="0" teleports="0" halting="0" stopped="0" meanWaitingTime="0.25" meanTravelTime="0.00" meanSpeed="8.02" meanSpeedRelative="0.84" duration="1682727802239"/>
    <step time="70.00" loaded="50" inserted="28" running="28" waiting="0" ended="22" arrived="0" collisions="0" teleports="0" halting="0" stopped="0" meanWaitingTime="0.25" meanTravelTime="0.00" meanSpeed="7.98" meanSpeedRelative="0.84" duration="1682727802280"/>
    <step time="71.00" loaded="50" inserted="28" running="28" waiting="0" ended="22" arrived="0" collisions="0" teleports="0" halting="0" stopped="0" meanWaitingTime="0.25" meanTravelTime="0.00" meanSpeed="7.72" meanSpeedRelative="0.82" duration="1682727802319"/>
    <step time="72.00" loaded="50" inserted="28" running="28" waiting="0" ended="22" arrived="0" collisions="0" teleports="0" halting="0" stopped="0" meanWaitingTime="0.25" meanTravelTime="0.00" meanSpeed="7.43" meanSpeedRelative="0.80" duration="1682727802359"/>
    <step time="73.00" loaded="50" inserted="28" running="28" waiting="0" ended="22" arrived="0" collisions="0" teleports="0" halting="1" stopped="0" meanWaitingTime="0.25" meanTravelTime="0.00" meanSpeed="7.48" meanSpeedRelative="0.80" duration="1682727802400"/>
    <step time="74.00" loaded="50" inserted="28" running="28" waiting="0" ended="22" arrived="0" collisions="0" teleports="0" halting="1" stopped="0" meanWaitingTime="0.25" meanTravelTime="0.00" meanSpeed="7.12" meanSpeedRelative="0.77" duration="1682727802442"/>
    <step time="75.00" loaded="50" inserted="28" running="28" waiting="0" ended="22" arrived="0" collisions="0" teleports="0" halting="1" stopped="0" meanWaitingTime="0.25" meanTravelTime="0.00" meanSpeed="7.14" meanSpeedRelative="0.78" duration="1682727802483"/>
    <step time="76.00" loaded="50" inserted="28" running="28" waiting="0" ended="22" arrived="0" collisions="0" teleports="0" halting="0" stopped="0" meanWaitingTime="0.25" meanTravelTime="0.00" meanSpeed="7.09" meanSpeedRelative="0.81" duration="1682727802526"/>
    <step time="77.00" loaded="50" inserted="28" running="28" waiting="0" ended="22" arrived="0" collisions="0" teleports="0" halting="0" stopped="0" meanWaitingTime="0.25" meanTravelTime="0.00" meanSpeed="6.94" meanSpeedRelative="0.82" duration="1682727802567"/>
    <step time="78.00" loaded="50" inserted="28" running="28" waiting="0" ended="22" arrived="0" collisions="0" teleports="0" halting="0" stopped="0" meanWaitingTime="0.25" meanTravelTime="0.00" meanSpeed="6.71" meanSpeedRelative="0.79" duration="1682727802607"/>
    <step time="79.00" loaded="50" inserted="28" running="28" waiting="0" ended="22" arrived="0" collisions="0" teleports="0" halting="0" stopped="0" meanWaitingTime="0.25" meanTravelTime="0.00" meanSpeed="6.40" meanSpeedRelative="0.78" duration="1682727802646"/>
    <step time="80.00" loaded="50" inserted="28" running="28" waiting="0" ended="22" arrived="0" collisions="0" teleports="0" halting="0" stopped="0" meanWaitingTime="0.25" meanTravelTime="0.00" meanSpeed="6.40" meanSpeedRelative="0.78" duration="1682727802683"/>
    <step time="81.00" loaded="50" inserted="28" running="28" waiting="0" ended="22" arrived="0" collisions="0" teleports="0" halting="0" stopped="0" meanWaitingTime="0.25" meanTravelTime="0.00" meanSpeed="6.44" meanSpeedRelative="0.77" duration="1682727802721"/>
    <step time="82.00" loaded="50" inserted="28" running="28" waiting="0" ended="22" arrived="0" collisions="0" teleports="0" halting="0" stopped="0" meanWaitingTime="0.25" meanTravelTime="0.00" meanSpeed="6.44" meanSpeedRelative="0.76" duration="1682727802759"/>
    <step time="83.00" loaded="52" inserted="28" running="28" waiting="0" ended="24" arrived="0" collisions="0" teleports="0" halting="2" stopped="1" meanWaitingTime="0.25" meanTravelTime="0.00" meanSpeed="6.67" meanSpeedRelative="0.76" duration="1682727802802"/>
    <step time="84.00" loaded="52" inserted="28" running="28" waiting="0" ended="24" arrived="0" collisions="0" teleports="0" halting="2" stopped="1" meanWaitingTime="0.25" meanTravelTime="0.00" meanSpeed="6.27" meanSpeedRelative="0.73" duration="1682727802842"/>
    <step time="85.00" loaded="54" inserted="28" running="28" waiting="0" ended="26" arrived="0" collisions="0" teleports="0" halting="2" stopped="1" meanWaitingTime="0.25" meanTravelTime="0.00" meanSpeed="6.05" meanSpeedRelative="0.72" duration="1682727802882"/>
    <step time="86.00" loaded="54" inserted="28" running="28" waiting="0" ended="26" arrived="0" collisions="0" teleports="0" halting="3" stopped="1" meanWaitingTime="0.25" meanTravelTime="0.00" meanSpeed="5.98" meanSpeedRelative="0.74" duration="1682727802919"/>
    <step time="87.00" loaded="54" inserted="28" running="28" waiting="0" ended="26" arrived="0" collisions="0" teleports="0" halting="5" stopped="2" meanWaitingTime="0.25" meanTravelTime="0.00" meanSpeed="5.88" meanSpeedRelative="0.71" duration="1682727803071"/>
    <step time="88.00" loaded="54" inserted="28" running="28" waiting="0" ended="26" arrived="0" collisions="0" teleports="0" halting="5" stopped="2" meanWaitingTime="0.25" meanTravelTime="0.00" meanSpeed="5.51" meanSpeedRelative="0.68" duration="1682727803114"/>
    <step time="89.00" loaded="54" inserted="28" running="28" waiting="0" ended="26" arrived="0" collisions="0" teleports="0" halting="6" stopped="2" meanWaitingTime="0.25" meanTravelTime="0.00" meanSpeed="5.20" meanSpeedRelative="0.65" duration="1682727803157"/>
    <step time="90.00" loaded="61" inserted="35" running="35" waiting="0" ended="26" arrived="0" collisions="0" teleports="0" halting="2" stopped="2" meanWaitingTime="0.20" meanTravelTime="0.00" meanSpeed="6.80" meanSpeedRelative="0.73" duration="1682727803202"/>
    <step time="91.00" loaded="63" inserted="35" running="35" waiting="0" ended="28" arrived="0" collisions="0" teleports="0" halting="2" stopped="2" meanWaitingTime="0.20" meanTravelTime="0.00" meanSpeed="6.87" meanSpeedRelative="0.85" duration="1682727803258"/>
    <step time="92.00" loaded="63" inserted="35" running="35" waiting="0" ended="28" arrived="0" collisions="0" teleports="0" halting="2" stopped="2" meanWaitingTime="0.20" meanTravelTime="0.00" meanSpeed="6.85" meanSpeedRelative="0.79" duration="1682727803307"/>
    <step time="93.00" loaded="63" inserted="35" running="35" waiting="0" ended="28" arrived="0" collisions="0" teleports="0" halting="2" stopped="2" meanWaitingTime="0.20" meanTravelTime="0.00" meanSpeed="6.86" meanSpeedRelative="0.79" duration="1682727803356"/>
    <step time="94.00" loaded="63" inserted="35" running="35" waiting="0" ended="28" arrived="0" collisions="0" teleports="0" halting="2" stopped="2" meanWaitingTime="0.20" meanTravelTime="0.00" meanSpeed="6.67" meanSpeedRelative="0.84" duration="1682727803407"/>
    <step time="95.00" loaded="63" inserted="35" running="35" waiting="0" ended="28" arrived="0" collisions="0" teleports="0" halting="2" stopped="2" meanWaitingTime="0.20" meanTravelTime="0.00" meanSpeed="6.77" meanSpeedRelative="0.82" duration="1682727803451"/>
    <step time="96.00" loaded="63" inserted="35" running="35" waiting="0" ended="28" arrived="0" collisions="0" teleports="0" halting="2" stopped="2" meanWaitingTime="0.20" meanTravelTime="0.00" meanSpeed="6.91" meanSpeedRelative="0.82" duration="1682727803499"/>
    <step time="97.00" loaded="63" inserted="35" running="34" waiting="0" ended="29" arrived="1" collisions="0" teleports="0" halting="4" stopped="4" meanWaitingTime="0.20" meanTravelTime="3.31" meanSpeed="7.14" meanSpeedRelative="0.84" duration="1682727803548"/>
    <step time="98.00" loaded="65" inserted="35" running="34" waiting="0" ended="31" arrived="1" collisions="0" teleports="0" halting="4" stopped="4" meanWaitingTime="0.20" meanTravelTime="3.10" meanSpeed="7.31" meanSpeedRelative="0.83" duration="1682727803600"/>
    <step time="99.00" loaded="67" inserted="35" running="34" waiting="0" ended="33" arrived="1" collisions="0" teleports="0" halting="5" stopped="4" meanWaitingTime="0.20" meanTravelTime="2.91" meanSpeed="7.50" meanSpeedRelative="0.83" duration="1682727803653"/>
    <step time="100.00" loaded="67" inserted="35" running="34" waiting="0" ended="33" arrived="1" collisions="0" teleports="0" halting="5" stopped="4" meanWaitingTime="0.20" meanTravelTime="2.91" meanSpeed="7.62" meanSpeedRelative="0.83" duration="1682727803702"/>
    <step time="101.00" loaded="67" inserted="35" running="34" waiting="0" ended="33" arrived="1" collisions="0" teleports="0" halting="5" stopped="4" meanWaitingTime="0.20" meanTravelTime="2.91" meanSpeed="7.74" meanSpeedRelative="0.84" duration="1682727803752"/>
    <step time="102.00" loaded="67" inserted="35" running="34" waiting="0" ended="33" arrived="1" collisions="0" teleports="0" halting="5" stopped="4" meanWaitingTime="0.20" meanTravelTime="2.91" meanSpeed="7.78" meanSpeedRelative="0.84" duration="1682727803801"/>
    <step time="103.00" loaded="67" inserted="35" running="34" waiting="0" ended="33" arrived="1" collisions="0" teleports="0" halting="5" stopped="4" meanWaitingTime="0.20" meanTravelTime="2.91" meanSpeed="7.83" meanSpeedRelative="0.87" duration="1682727803849"/>
    <step time="104.00" loaded="67" inserted="35" running="34" waiting="0" ended="33" arrived="1" collisions="0" teleports="0" halting="5" stopped="4" meanWaitingTime="0.20" meanTravelTime="2.91" meanSpeed="7.86" meanSpeedRelative="0.89" duration="1682727803900"/>
    <step time="105.00" loaded="67" inserted="35" running="34" waiting="0" ended="33" arrived="1" collisions="0" teleports="0" halting="5" stopped="4" meanWaitingTime="0.20" meanTravelTime="2.91" meanSpeed="7.72" meanSpeedRelative="0.88" duration="1682727803951"/>
    <step time="106.00" loaded="67" inserted="35" running="34" waiting="0" ended="33" arrived="1" collisions="0" teleports="0" halting="5" stopped="4" meanWaitingTime="0.20" meanTravelTime="2.91" meanSpeed="7.23" meanSpeedRelative="0.83" duration="1682727804103"/>
    <step time="107.00" loaded="67" inserted="35" running="34" waiting="0" ended="33" arrived="1" collisions="0" teleports="0" halting="5" stopped="4" meanWaitingTime="0.20" meanTravelTime="2.91" meanSpeed="6.93" meanSpeedRelative="0.81" duration="1682727804153"/>
    <step time="108.00" loaded="67" inserted="35" running="34" waiting="0" ended="33" arrived="1" collisions="0" teleports="0" halting="5" stopped="4" meanWaitingTime="0.20" meanTravelTime="2.91" meanSpeed="6.84" meanSpeedRelative="0.81" duration="1682727804201"/>
    <step time="109.00" loaded="67" inserted="35" running="33" waiting="0" ended="34" arrived="2" collisions="0" teleports="0" halting="5" stopped="4" meanWaitingTime="0.20" meanTravelTime="6.00" meanSpeed="6.53" meanSpeedRelative="0.81" duration="1682727804250"/>
    <step time="110.00" loaded="67" inserted="35" running="33" waiting="0" ended="34" arrived="2" collisions="0" teleports="0" halting="5" stopped="4" meanWaitingTime="0.20" meanTravelTime="6.00" meanSpeed="6.26" meanSpeedRelative="0.79" duration="1682727804300"/>
    <step time="111.00" loaded="67" inserted="35" running="33" waiting="0" ended="34" arrived="2" collisions="0" teleports="0" halting="5" stopped="4" meanWaitingTime="0.20" meanTravelTime="6.00" meanSpeed="6.22" meanSpeedRelative="0.78" duration="1682727804351"/>
    <step time="112.00" loaded="67" inserted="35" running="33" waiting="0" ended="34" arrived="2" collisions="0" teleports="0" halting="5" stopped="4" meanWaitingTime="0.20" meanTravelTime="6.00" meanSpeed="6.03" meanSpeedRelative="0.78" duration="1682727804401"/>
    <step time="113.00" loaded="67" inserted="35" running="33" waiting="0" ended="34" arrived="2" collisions="0" teleports="0" halting="5" stopped="4" meanWaitingTime="0.20" meanTravelTime="6.00" meanSpeed="6.02" meanSpeedRelative="0.79" duration="1682727804452"/>
    <step time="114.00" loaded="67" inserted="35" running="33" waiting="0" ended="34" arrived="2" collisions="0" teleports="0" halting="6" stopped="4" meanWaitingTime="0.20" meanTravelTime="6.00" meanSpeed="5.94" meanSpeedRelative="0.79" duration="1682727804503"/>
    <step time="115.00" loaded="67" inserted="35" running="33" waiting="0" ended="34" arrived="2" collisions="0" teleports="0" halting="6" stopped="4" meanWaitingTime="0.20" meanTravelTime="6.00" meanSpeed="5.94" meanSpeedRelative="0.82" duration="1682727804550"/>
    <step time="116.00" loaded="67" inserted="35" running="33" waiting="0" ended="34" arrived="2" collisions="0" teleports="0" halting="6" stopped="4" meanWaitingTime="0.20" meanTravelTime="6.00" meanSpeed="6.00" meanSpeedRelative="0.82" duration="1682727804598"/>
    <step time="117.00" loaded="67" inserted="35" running="33" waiting="0" ended="34" arrived="2" collisions="0" teleports="0" halting="6" stopped="4" meanWaitingTime="0.20" meanTravelTime="6.00" meanSpeed="6.01" meanSpeedRelative="0.88" duration="1682727804642"/>
    <step time="118.00" loaded="67" inserted="35" running="33" waiting="0" ended="34" arrived="2" collisions="0" teleports="0" halting="6" stopped="4" meanWaitingTime="0.20" meanTravelTime="6.00" meanSpeed="6.04" meanSpeedRelative="0.82" duration="1682727804692"/>
    <step time="119.00" loaded="67" inserted="35" running="33" waiting="0" ended="34" arrived="2" collisions="0" teleports="0" halting="6" stopped="4" meanWaitingTime="0.20" meanTravelTime="6.00" meanSpeed="6.08" meanSpeedRelative="0.82" duration="1682727804743"/>
    <step time="120.00" loaded="74" inserted="42" running="40" waiting="0" ended="34" arrived="2" collisions="0" teleports="0" halting="6" stopped="4" meanWaitingTime="0.17" meanTravelTime="6.00" meanSpeed="7.26" meanSpeedRelative="0.85" duration="1682727804795"/>
    <step time="121.00" loaded="78" inserted="42" running="40" waiting="0" ended="38" arrived="2" collisions="0" teleports="0" halting="6" stopped="4" meanWaitingTime="0.17" meanTravelTime="5.37" meanSpeed="7.22" meanSpeedRelative="0.82" duration="1682727804861"/>
    <step time="122.00" loaded="78" inserted="42" running="40" waiting="0" ended="38" arrived="2" collisions="0" teleports="0" halting="6" stopped="4" meanWaitingTime="0.17" meanTravelTime="5.37" meanSpeed="7.02" meanSpeedRelative="0.82" duration="1682727804923"/>
    <step time="123.00" loaded="78" inserted="42" running="40" waiting="0" ended="38" arrived="2" collisions="0" teleports="0" halting="6" stopped="4" meanWaitingTime="0.17" meanTravelTime="5.37" meanSpeed="6.86" meanSpeedRelative="0.81" duration="1682727804982"/>
    <step time="124.00" loaded="80" inserted="42" running="40" waiting="0" ended="40" arrived="2" collisions="0" teleports="0" halting="6" stopped="4" meanWaitingTime="0.17" meanTravelTime="5.10" meanSpeed="6.68" meanSpeedRelative="0.79" duration="1682727805142"/>
    <step time="125.00" loaded="80" inserted="42" running="40" waiting="0" ended="40" arrived="2" collisions="0" teleports="0" halting="6" stopped="4" meanWaitingTime="0.17" meanTravelTime="5.10" meanSpeed="6.48" meanSpeedRelative="0.75" duration="1682727805195"/>
    <step time="126.00" loaded="80" inserted="42" running="40" waiting="0" ended="40" arrived="2" collisions="0" teleports="0" halting="7" stopped="4" meanWaitingTime="0.17" meanTravelTime="5.10" meanSpeed="6.41" meanSpeedRelative="0.76" duration="1682727805252"/>
    <step time="127.00" loaded="80" inserted="42" running="40" waiting="0" ended="40" arrived="2" collisions="0" teleports="0" halting="7" stopped="4" meanWaitingTime="0.17" meanTravelTime="5.10" meanSpeed="6.38" meanSpeedRelative="0.76" duration="1682727805314"/>
    <step time="128.00" loaded="80" inserted="42" running="40" waiting="0" ended="40" arrived="2" collisions="0" teleports="0" halting="7" stopped="4" meanWaitingTime="0.17" meanTravelTime="5.10" meanSpeed="6.36" meanSpeedRelative="0.74" duration="1682727805373"/>
    <step time="129.00" loaded="82" inserted="42" running="40" waiting="0" ended="42" arrived="2" collisions="0" teleports="0" halting="7" stopped="4" meanWaitingTime="0.17" meanTravelTime="4.86" meanSpeed="6.52" meanSpeedRelative="0.76" duration="1682727805441"/>
    <step time="130.00" loaded="82" inserted="42" running="40" waiting="0" ended="42" arrived="2" collisions="0" teleports="0" halting="7" stopped="4" meanWaitingTime="0.17" meanTravelTime="4.86" meanSpeed="6.57" meanSpeedRelative="0.76" duration="1682727805502"/>
    <step time="131.00" loaded="84" inserted="42" running="40" waiting="0" ended="44" arrived="2" collisions="0" teleports="0" halting="7" stopped="4" meanWaitingTime="0.17" meanTravelTime="4.64" meanSpeed="6.53" meanSpeedRelative="0.76" duration="1682727805564"/>
    <step time="132.00" loaded="86" inserted="42" running="40" waiting="0" ended="46" arrived="2" collisions="0" teleports="0" halting="7" stopped="4" meanWaitingTime="0.17" meanTravelTime="4.43" meanSpeed="6.44" meanSpeedRelative="0.77" duration="1682727805625"/>
    <step time="133.00" loaded="86" inserted="42" running="40" waiting="0" ended="46" arrived="2" collisions="0" teleports="0" halting="7" stopped="4" meanWaitingTime="0.17" meanTravelTime="4.43" meanSpeed="6.54" meanSpeedRelative="0.77" duration="1682727805685"/>
    <step time="134.00" loaded="86" inserted="42" running="40" waiting="0" ended="46" arrived="2" collisions="0" teleports="0" halting="7" stopped="4" meanWaitingTime="0.17" meanTravelTime="4.43" meanSpeed="6.36" meanSpeedRelative="0.75" duration="1682727805740"/>
    <step time="135.00" loaded="86" inserted="42" running="40" waiting="0" ended="46" arrived="2" collisions="0" teleports="0" halting="8" stopped="5" meanWaitingTime="0.17" meanTravelTime="4.43" meanSpeed="6.38" meanSpeedRelative="0.76" duration="1682727805797"/>
    <step time="136.00" loaded="86" inserted="42" running="40" waiting="0" ended="46" arrived="2" collisions="0" teleports="0" halting="8" stopped="5" meanWaitingTime="0.17" meanTravelTime="4.43" meanSpeed="6.17" meanSpeedRelative="0.75" duration="1682727805853"/>
    <step time="137.00" loaded="88" inserted="42" running="40" waiting="0" ended="48" arrived="2" collisions="0" teleports="0" halting="9" stopped="6" meanWaitingTime="0.17" meanTravelTime="4.25" meanSpeed="6.14" meanSpeedRelative="0.72" duration="1682727805917"/>
    <step time="138.00" loaded="88" inserted="42" running="40" waiting="0" ended="48" arrived="2" collisions="0" teleports="0" halting="9" stopped="6" meanWaitingTime="0.17" meanTravelTime="4.25" meanSpeed="5.97" meanSpeedRelative="0.71" duration="1682727805976"/>
    <step time="139.00" loaded="88" inserted="42" running="40" waiting="0" ended="48" arrived="2" collisions="0" teleports="0" halting="9" stopped="6" meanWaitingTime="0.17" meanTravelTime="4.25" meanSpeed="5.72" meanSpeedRelative="0.69" duration="1682727806037"/>
    <step time="140.00" loaded="88" inserted="42" running="40" waiting="0" ended="48" arrived="2" collisions="0" teleports="0" halting="10" stopped="7" meanWaitingTime="0.17" meanTravelTime="4.25" meanSpeed="5.54" meanSpeedRelative="0.67" duration="1682727806213"/>
    <step time="141.00" loaded="88" inserted="42" running="40" waiting="0" ended="48" arrived="2" collisions="0" teleports="0" halting="10" stopped="7" meanWaitingTime="0.17" meanTravelTime="4.25" meanSpeed="5.52" meanSpeedRelative="0.67" duration="1682727806278"/>
    <step time="142.00" loaded="88" inserted="42" running="40" waiting="0" ended="48" arrived="2" collisions="0" teleports="0" halting="11" stopped="7" meanWaitingTime="0.17" meanTravelTime="4.25" meanSpeed="5.46" meanSpeedRelative="0.69" duration="1682727806340"/>
    <step time="143.00" loaded="88" inserted="42" running="40" waiting="0" ended="48" arrived="2" collisions="0" teleports="0" halting="11" stopped="7" meanWaitingTime="0.17" meanTravelTime="4.25" meanSpeed="5.31" meanSpeedRelative="0.66" duration="1682727806402"/>
    <step time="144.00" loaded="88" inserted="42" running="40" waiting="0" ended="48" arrived="2" collisions="0" teleports="0" halting="11" stopped="7" meanWaitingTime="0.17" meanTravelTime="4.25" meanSpeed="5.29" meanSpeedRelative="0.67" duration="1682727806457"/>
    <step time="145.00" loaded="88" inserted="42" running="40" waiting="0" ended="48" arrived="2" collisions="0" teleports="0" halting="11" stopped="7" meanWaitingTime="0.17" meanTravelTime="4.25" meanSpeed="5.45" meanSpeedRelative="0.68" duration="1682727806512"/>
    <step time="146.00" loaded="88" inserted="42" running="40" waiting="0" ended="48" arrived="2" collisions="0" teleports="0" halting="11" stopped="7" meanWaitingTime="0.17" meanTravelTime="4.25" meanSpeed="5.38" meanSpeedRelative="0.68" duration="1682727806568"/>
    <step time="147.00" loaded="88" inserted="42" running="40" waiting="0" ended="48" arrived="2" collisions="0" teleports="0" halting="11" stopped="7" meanWaitingTime="0.17" meanTravelTime="4.25" meanSpeed="5.37" meanSpeedRelative="0.67" duration="1682727806622"/>
    <step time="148.00" loaded="88" inserted="42" running="40" waiting="0" ended="48" arrived="2" collisions="0" teleports="0" halting="11" stopped="7" meanWaitingTime="0.17" meanTravelTime="4.25" meanSpeed="5.51" meanSpeedRelative="0.68" duration="1682727806679"/>
    <step time="149.00" loaded="88" inserted="42" running="40" waiting="0" ended="48" arrived="2" collisions="0" teleports="0" halting="12" stopped="7" meanWaitingTime="0.17" meanTravelTime="4.25" meanSpeed="5.57" meanSpeedRelative="0.67" duration="1682727806734"/>
    <step time="150.00" loaded="102" inserted="49" running="47" waiting="7" ended="48" arrived="2" collisions="0" teleports="0" halting="12" stopped="7" meanWaitingTime="0.14" meanTravelTime="4.25" meanSpeed="6.92" meanSpeedRelative="0.73" duration="1682727806788"/>
    <step time="151.00" loaded="106" inserted="56" running="54" waiting="0" ended="52" arrived="2" collisions="0" teleports="0" halting="13" stopped="7" meanWaitingTime="0.25" meanTravelTime="3.92" meanSpeed="7.36" meanSpeedRelative="0.76" duration="1682727806858"/>
    <step time="152.00" loaded="108" inserted="56" running="53" waiting="0" ended="55" arrived="3" collisions="0" teleports="0" halting="13" stopped="7" meanWaitingTime="0.25" meanTravelTime="6.45" meanSpeed="7.18" meanSpeedRelative="0.73" duration="1682727806928"/>
    <step time="153.00" loaded="110" inserted="56" running="53" waiting="0" ended="57" arrived="3" collisions="0" teleports="0" halting="12" stopped="7" meanWaitingTime="0.25" meanTravelTime="6.23" meanSpeed="7.38" meanSpeedRelative="0.77" duration="1682727806995"/>
    <step time="154.00" loaded="112" inserted="56" running="53" waiting="0" ended="59" arrived="3" collisions="0" teleports="0" halting="12" stopped="7" meanWaitingTime="0.25" meanTravelTime="6.02" meanSpeed="7.34" meanSpeedRelative="0.76" duration="1682727807059"/>
    <step time="155.00" loaded="112" inserted="56" running="52" waiting="0" ended="60" arrived="4" collisions="0" teleports="0" halting="12" stopped="7" meanWaitingTime="0.25" meanTravelTime="8.50" meanSpeed="7.27" meanSpeedRelative="0.73" duration="1682727807231"/>
    <step time="156.00" loaded="112" inserted="56" running="52" waiting="0" ended="60" arrived="4" collisions="0" teleports="0" halting="12" stopped="7" meanWaitingTime="0.25" meanTravelTime="8.50" meanSpeed="7.08" meanSpeedRelative="0.74" duration="1682727807296"/>
    <step time="157.00" loaded="112" inserted="56" running="52" waiting="0" ended="60" arrived="4" collisions="0" teleports="0" halting="13" stopped="7" meanWaitingTime="0.25" meanTravelTime="8.50" meanSpeed="7.05" meanSpeedRelative="0.72" duration="1682727807361"/>
    <step time="158.00" loaded="112" inserted="56" running="52" waiting="0" ended="60" arrived="4" collisions="0" teleports="0" halting="13" stopped="7" meanWaitingTime="0.25" meanTravelTime="8.50" meanSpeed="6.95" meanSpeedRelative="0.72" duration="1682727807431"/>
    <step time="159.00" loaded="114" inserted="56" running="52" waiting="0" ended="62" arrived="4" collisions="0" teleports="0" halting="13" stopped="7" meanWaitingTime="0.25" meanTravelTime="8.23" meanSpeed="6.84" meanSpeedRelative="0.70" duration="1682727807503"/>
    <step time="160.00" loaded="114" inserted="56" running="51" waiting="0" ended="63" arrived="5" collisions="0" teleports="0" halting="13" stopped="7" meanWaitingTime="0.25" meanTravelTime="10.62" meanSpeed="6.72" meanSpeedRelative="0.68" duration="1682727807569"/>
    <step time="161.00" loaded="114" inserted="56" running="51" waiting="0" ended="63" arrived="5" collisions="0" teleports="0" halting="14" stopped="7" meanWaitingTime="0.25" meanTravelTime="10.62" meanSpeed="6.63" meanSpeedRelative="0.72" duration="1682727807632"/>
    <step time="162.00" loaded="114" inserted="56" running="50" waiting="0" ended="64" arrived="6" collisions="0" teleports="0" halting="14" stopped="7" meanWaitingTime="0.25" meanTravelTime="11.58" meanSpeed="6.17" meanSpeedRelative="0.67" duration="1682727807697"/>
    <step time="163.00" loaded="114" inserted="56" running="50" waiting="0" ended="64" arrived="6" collisions="0" teleports="0" halting="15" stopped="6" meanWaitingTime="0.25" meanTravelTime="11.58" meanSpeed="5.85" meanSpeedRelative="0.64" duration="1682727807762"/>
    <step time="164.00" loaded="114" inserted="56" running="50" waiting="0" ended="64" arrived="6" collisions="0" teleports="0" halting="14" stopped="6" meanWaitingTime="0.25" meanTravelTime="11.58" meanSpeed="5.73" meanSpeedRelative="0.66" duration="1682727807825"/>
    <step time="165.00" loaded="114" inserted="56" running="49" waiting="0" ended="65" arrived="7" collisions="0" teleports="0" halting="14" stopped="6" meanWaitingTime="0.25" meanTravelTime="13.92" meanSpeed="5.60" meanSpeedRelative="0.69" duration="1682727807888"/>
    <step time="166.00" loaded="114" inserted="56" running="49" waiting="0" ended="65" arrived="7" collisions="0" teleports="0" halting="13" stopped="6" meanWaitingTime="0.25" meanTravelTime="13.92" meanSpeed="5.52" meanSpeedRelative="0.71" duration="1682727807952"/>
    <step time="167.00" loaded="114" inserted="56" running="49" waiting="0" ended="65" arrived="7" collisions="0" teleports="0" halting="13" stopped="5" meanWaitingTime="0.25" meanTravelTime="13.92" meanSpeed="5.31" meanSpeedRelative="0.72" duration="1682727808013"/>
    <step time="168.00" loaded="114" inserted="56" running="49" waiting="0" ended="65" arrived="7" collisions="0" teleports="0" halting="12" stopped="5" meanWaitingTime="0.25" meanTravelTime="13.92" meanSpeed="5.27" meanSpeedRelative="0.65" duration="1682727808073"/>
    <step time="169.00" loaded="114" inserted="56" running="49" waiting="0" ended="65" arrived="7" collisions="0" teleports="0" halting="11" stopped="5" meanWaitingTime="0.25" meanTravelTime="13.92" meanSpeed="5.09" meanSpeedRelative="0.67" duration="1682727808237"/>
    <step time="170.00" loaded="114" inserted="56" running="49" waiting="0" ended="65" arrived="7" collisions="0" teleports="0" halting="10" stopped="5" meanWaitingTime="0.25" meanTravelTime="13.92" meanSpeed="5.03" meanSpeedRelative="0.72" duration="1682727808297"/>
    <step time="171.00" loaded="116" inserted="56" running="49" waiting="0" ended="67" arrived="7" collisions="0" teleports="0" halting="10" stopped="5" meanWaitingTime="0.25" meanTravelTime="13.51" meanSpeed="4.95" meanSpeedRelative="0.76" duration="1682727808360"/>
    <step time="172.00" loaded="116" inserted="56" running="49" waiting="0" ended="67" arrived="7" collisions="0" teleports="0" halting="10" stopped="5" meanWaitingTime="0.25" meanTravelTime="13.51" meanSpeed="4.79" meanSpeedRelative="0.76" duration="1682727808424"/>
    <step time="173.00" loaded="116" inserted="56" running="49" waiting="0" ended="67" arrived="7" collisions="0" teleports="0" halting="11" stopped="5" meanWaitingTime="0.25" meanTravelTime="13.51" meanSpeed="4.60" meanSpeedRelative="0.68" duration="1682727808484"/>
    <step time="174.00" loaded="116" inserted="56" running="49" waiting="0" ended="67" arrived="7" collisions="0" teleports="0" halting="12" stopped="5" meanWaitingTime="0.25" meanTravelTime="13.51" meanSpeed="4.33" meanSpeedRelative="0.67" duration="1682727808547"/>
    <step time="175.00" loaded="116" inserted="56" running="49" waiting="0" ended="67" arrived="7" collisions="0" teleports="0" halting="13" stopped="5" meanWaitingTime="0.25" meanTravelTime="13.51" meanSpeed="4.12" meanSpeedRelative="0.65" duration="1682727808607"/>
    <step time="176.00" loaded="116" inserted="56" running="49" waiting="0" ended="67" arrived="7" collisions="0" teleports="0" halting="15" stopped="6" meanWaitingTime="0.25" meanTravelTime="13.51" meanSpeed="4.12" meanSpeedRelative="0.64" duration="1682727808666"/>
    <step time="177.00" loaded="116" inserted="56" running="49" waiting="0" ended="67" arrived="7" collisions="0" teleports="0" halting="16" stopped="4" meanWaitingTime="0.25" meanTravelTime="13.51" meanSpeed="3.86" meanSpeedRelative="0.58" duration="1682727808725"/>
    <step time="178.00" loaded="116" inserted="56" running="49" waiting="0" ended="67" arrived="7" collisions="0" teleports="0" halting="16" stopped="4" meanWaitingTime="0.25" meanTravelTime="13.51" meanSpeed="3.68" meanSpeedRelative="0.58" duration="1682727808785"/>
    <step time="179.00" loaded="116" inserted="56" running="49" waiting="0" ended="67" arrived="7" collisions="0" teleports="0" halting="16" stopped="4" meanWaitingTime="0.25" meanTravelTime="13.51" meanSpeed="3.72" meanSpeedRelative="0.64" duration="1682727808846"/>
    <step time="180.00" loaded="123" inserted="63" running="56" waiting="0" ended="67" arrived="7" collisions="0" teleports="0" halting="9" stopped="4" meanWaitingTime="0.22" meanTravelTime="13.51" meanSpeed="5.01" meanSpeedRelative="0.73" duration="1682727808913"/>
    <step time="181.00" loaded="125" inserted="63" running="56" waiting="0" ended="69" arrived="7" collisions="0" teleports="0" halting="8" stopped="4" meanWaitingTime="0.22" meanTravelTime="13.12" meanSpeed="5.18" meanSpeedRelative="0.74" duration="1682727808993"/>
    <step time="182.00" loaded="125" inserted="63" running="56" waiting="0" ended="69" arrived="7" collisions="0" teleports="0" halting="7" stopped="4" meanWaitingTime="0.22" meanTravelTime="13.12" meanSpeed="5.31" meanSpeedRelative="0.77" duration="1682727809067"/>
    <step time="183.00" loaded="125" inserted="63" running="56" waiting="0" ended="69" arrived="7" collisions="0" teleports="0" halting="7" stopped="4" meanWaitingTime="0.22" meanTravelTime="13.12" meanSpeed="5.32" meanSpeedRelative="0.74" duration="1682727809137"/>
    <step time="184.00" loaded="129" inserted="63" running="55" waiting="0" ended="74" arrived="8" collisions="0" teleports="0" halting="8" stopped="4" meanWaitingTime="0.22" meanTravelTime="14.70" meanSpeed="5.24" meanSpeedRelative="0.71" duration="1682727809316"/>
    <step time="185.00" loaded="129" inserted="63" running="55" waiting="0" ended="74" arrived="8" collisions="0" teleports="0" halting="8" stopped="4" meanWaitingTime="0.22" meanTravelTime="14.70" meanSpeed="5.28" meanSpeedRelative="0.71" duration="1682727809381"/>
    <step time="186.00" loaded="129" inserted="63" running="55" waiting="0" ended="74" arrived="8" collisions="0" teleports="0" halting="8" stopped="4" meanWaitingTime="0.22" meanTravelTime="14.70" meanSpeed="5.24" meanSpeedRelative="0.72" duration="1682727809446"/>
    <step time="187.00" loaded="129" inserted="63" running="55" waiting="0" ended="74" arrived="8" collisions="0" teleports="0" halting="9" stopped="5" meanWaitingTime="0.22" meanTravelTime="14.70" meanSpeed="5.25" meanSpeedRelative="0.70" duration="1682727809511"/>
    <step time="188.00" loaded="129" inserted="63" running="54" waiting="0" ended="75" arrived="9" collisions="0" teleports="0" halting="9" stopped="5" meanWaitingTime="0.22" meanTravelTime="16.61" meanSpeed="5.14" meanSpeedRelative="0.67" duration="1682727809578"/>
    <step time="189.00" loaded="129" inserted="63" running="53" waiting="0" ended="76" arrived="10" collisions="0" teleports="0" halting="13" stopped="6" meanWaitingTime="0.22" meanTravelTime="18.87" meanSpeed="4.93" meanSpeedRelative="0.68" duration="1682727809644"/>
    <step time="190.00" loaded="129" inserted="63" running="53" waiting="0" ended="76" arrived="10" collisions="0" teleports="0" halting="15" stopped="6" meanWaitingTime="0.22" meanTravelTime="18.87" meanSpeed="4.96" meanSpeedRelative="0.65" duration="1682727809713"/>
    <step time="191.00" loaded="129" inserted="63" running="53" waiting="0" ended="76" arrived="10" collisions="0" teleports="0" halting="15" stopped="6" meanWaitingTime="0.22" meanTravelTime="18.87" meanSpeed="5.14" meanSpeedRelative="0.66" duration="1682727809778"/>
    <step time="192.00" loaded="129" inserted="63" running="53" waiting="0" ended="76" arrived="10" collisions="0" teleports="0" halting="14" stopped="6" meanWaitingTime="0.22" meanTravelTime="18.87" meanSpeed="5.39" meanSpeedRelative="0.68" duration="1682727809844"/>
    <step time="193.00" loaded="129" inserted="63" running="53" waiting="0" ended="76" arrived="10" collisions="0" teleports="0" halting="14" stopped="6" meanWaitingTime="0.22" meanTravelTime="18.87" meanSpeed="5.57" meanSpeedRelative="0.69" duration="1682727809914"/>
    <step time="194.00" loaded="129" inserted="63" running="53" waiting="0" ended="76" arrived="10" collisions="0" teleports="0" halting="14" stopped="6" meanWaitingTime="0.22" meanTravelTime="18.87" meanSpeed="5.62" meanSpeedRelative="0.71" duration="1682727809981"/>
    <step time="195.00" loaded="129" inserted="63" running="53" waiting="0" ended="76" arrived="10" collisions="0" teleports="0" halting="14" stopped="6" meanWaitingTime="0.22" meanTravelTime="18.87" meanSpeed="5.53" meanSpeedRelative="0.71" duration="1682727810050"/>
    <step time="196.00" loaded="129" inserted="63" running="53" waiting="0" ended="76" arrived="10" collisions="0" teleports="0" halting="14" stopped="6" meanWaitingTime="0.22" meanTravelTime="18.87" meanSpeed="5.50" meanSpeedRelative="0.72" duration="1682727810124"/>
    <step time="197.00" loaded="129" inserted="63" running="53" waiting="0" ended="76" arrived="10" collisions="0" teleports="0" halting="14" stopped="6" meanWaitingTime="0.22" meanTravelTime="18.87" meanSpeed="5.47" meanSpeedRelative="0.70" duration="1682727810190"/>
    <step time="198.00" loaded="129" inserted="63" running="53" waiting="0" ended="76" arrived="10" collisions="0" teleports="0" halting="14" stopped="6" meanWaitingTime="0.22" meanTravelTime="18.87" meanSpeed="5.41" meanSpeedRelative="0.68" duration="1682727810368"/>
    <step time="199.00" loaded="129" inserted="63" running="53" waiting="0" ended="76" arrived="10" collisions="0" teleports="0" halting="14" stopped="6" meanWaitingTime="0.22" meanTravelTime="18.87" meanSpeed="5.30" meanSpeedRelative="0.70" duration="1682727810445"/>
    <step time="200.00" loaded="129" inserted="63" running="53" waiting="0" ended="76" arrived="10" collisions="0" teleports="0" halting="14" stopped="6" meanWaitingTime="0.22" meanTravelTime="18.87" meanSpeed="5.22" meanSpeedRelative="0.68" duration="1682727810522"/>
    <step time="201.00" loaded="129" inserted="63" running="53" waiting="0" ended="76" arrived="10" collisions="0" teleports="0" halting="15" stopped="6" meanWaitingTime="0.22" meanTravelTime="18.87" meanSpeed="5.16" meanSpeedRelative="0.67" duration="1682727810601"/>
    <step time="202.00" loaded="129" inserted="63" running="53" waiting="0" ended="76" arrived="10" collisions="0" teleports="0" halting="17" stopped="7" meanWaitingTime="0.22" meanTravelTime="18.87" meanSpeed="5.14" meanSpeedRelative="0.65" duration="1682727810675"/>
    <step time="203.00" loaded="131" inserted="63" running="53" waiting="0" ended="78" arrived="10" collisions="0" teleports="0" halting="17" stopped="7" meanWaitingTime="0.22" meanTravelTime="18.38" meanSpeed="5.21" meanSpeedRelative="0.65" duration="1682727810748"/>
    <step time="204.00" loaded="131" inserted="63" running="53" waiting="0" ended="78" arrived="10" collisions="0" teleports="0" halting="17" stopped="7" meanWaitingTime="0.22" meanTravelTime="18.38" meanSpeed="5.34" meanSpeedRelative="0.65" duration="1682727810821"/>
    <step time="205.00" loaded="131" inserted="63" running="53" waiting="0" ended="78" arrived="10" collisions="0" teleports="0" halting="17" stopped="7" meanWaitingTime="0.22" meanTravelTime="18.38" meanSpeed="5.56" meanSpeedRelative="0.67" duration="1682727810898"/>
    <step time="206.00" loaded="131" inserted="63" running="53" waiting="0" ended="78" arrived="10" collisions="0" teleports="0" halting="18" stopped="7" meanWaitingTime="0.22" meanTravelTime="18.38" meanSpeed="5.57" meanSpeedRelative="0.64" duration="1682727810977"/>
    <step time="207.00" loaded="131" inserted="63" running="53" waiting="0" ended="78" arrived="10" collisions="0" teleports="0" halting="19" stopped="7" meanWaitingTime="0.22" meanTravelTime="18.38" meanSpeed="5.56" meanSpeedRelative="0.61" duration="1682727811055"/>
    <step time="208.00" loaded="133" inserted="63" running="53" waiting="0" ended="80" arrived="10" collisions="0" teleports="0" halting="20" stopped="7" meanWaitingTime="0.22" meanTravelTime="17.93" meanSpeed="5.57" meanSpeedRelative="0.62" duration="1682727811135"/>
    <step time="209.00" loaded="133" inserted="63" running="53" waiting="0" ended="80" arrived="10" collisions="0" teleports="0" halting="20" stopped="7" meanWaitingTime="0.22" meanTravelTime="17.93" meanSpeed="5.66" meanSpeedRelative="0.61" duration="1682727811212"/>
    <step time="210.00" loaded="140" inserted="70" running="60" waiting="0" ended="80" arrived="10" collisions="0" teleports="0" halting="21" stopped="7" meanWaitingTime="0.20" meanTravelTime="17.93" meanSpeed="6.54" meanSpeedRelative="0.65" duration="1682727811387"/>
    <step time="211.00" loaded="140" inserted="70" running="60" waiting="0" ended="80" arrived="10" collisions="0" teleports="0" halting="21" stopped="7" meanWaitingTime="0.20" meanTravelTime="17.93" meanSpeed="6.43" meanSpeedRelative="0.64" duration="1682727811476"/>
    <step time="212.00" loaded="140" inserted="70" running="60" waiting="0" ended="80" arrived="10" collisions="0" teleports="0" halting="21" stopped="7" meanWaitingTime="0.20" meanTravelTime="17.93" meanSpeed="6.40" meanSpeedRelative="0.64" duration="1682727811555"/>
    <step time="213.00" loaded="140" inserted="70" running="60" waiting="0" ended="80" arrived="10" collisions="0" teleports="0" halting="22" stopped="7" meanWaitingTime="0.20" meanTravelTime="17.93" meanSpeed="6.30" meanSpeedRelative="0.62" duration="1682727811633"/>
    <step time="214.00" loaded="142" inserted="70" running="60" waiting="0" ended="82" arrived="10" collisions="0" teleports="0" halting="23" stopped="7" meanWaitingTime="0.20" meanTravelTime="17.49" meanSpeed="6.09" meanSpeedRelative="0.60" duration="1682727811713"/>
    <step time="215.00" loaded="142" inserted="70" running="60" waiting="0" ended="82" arrived="10" collisions="0" teleports="0" halting="24" stopped="6" meanWaitingTime="0.20" meanTravelTime="17.49" meanSpeed="5.92" meanSpeedRelative="0.58" duration="1682727811789"/>
    <step time="216.00" loaded="142" inserted="70" running="60" waiting="0" ended="82" arrived="10" collisions="0" teleports="0" halting="22" stopped="6" meanWaitingTime="0.20" meanTravelTime="17.49" meanSpeed="5.72" meanSpeedRelative="0.58" duration="1682727811865"/>
    <step time="217.00" loaded="142" inserted="70" running="60" waiting="0" ended="82" arrived="10" collisions="0" teleports="0" halting="21" stopped="5" meanWaitingTime="0.20" meanTravelTime="17.49" meanSpeed="5.37" meanSpeedRelative="0.59" duration="1682727811943"/>
    <step time="218.00" loaded="142" inserted="70" running="60" waiting="0" ended="82" arrived="10" collisions="0" teleports="0" halting="20" stopped="5" meanWaitingTime="0.20" meanTravelTime="17.49" meanSpeed="5.29" meanSpeedRelative="0.56" duration="1682727812025"/>
    <step time="219.00" loaded="142" inserted="70" running="60" waiting="0" ended="82" arrived="10" collisions="0" teleports="0" halting="19" stopped="5" meanWaitingTime="0.20" meanTravelTime="17.49" meanSpeed="5.24" meanSpeedRelative="0.59" duration="1682727812105"/>
    <step time="220.00" loaded="144" inserted="70" running="60" waiting="0" ended="84" arrived="10" collisions="0" teleports="0" halting="19" stopped="4" meanWaitingTime="0.20" meanTravelTime="17.07" meanSpeed="5.25" meanSpeedRelative="0.60" duration="1682727812187"/>
    <step time="221.00" loaded="144" inserted="70" running="60" waiting="0" ended="84" arrived="10" collisions="0" teleports="0" halting="17" stopped="4" meanWaitingTime="0.20" meanTravelTime="17.07" meanSpeed="5.24" meanSpeedRelative="0.64" duration="1682727812263"/>
    <step time="222.00" loaded="144" inserted="70" running="60" waiting="0" ended="84" arrived="10" collisions="0" teleports="0" halting="16" stopped="4" meanWaitingTime="0.20" meanTravelTime="17.07" meanSpeed="5.27" meanSpeedRelative="0.74" duration="1682727812448"/>
    <step time="223.00" loaded="144" inserted="70" running="60" waiting="0" ended="84" arrived="10" collisions="0" teleports="0" halting="17" stopped="4" meanWaitingTime="0.20" meanTravelTime="17.07" meanSpeed="5.22" meanSpeedRelative="0.66" duration="1682727812524"/>
    <step time="224.00" loaded="144" inserted="70" running="59" waiting="0" ended="85" arrived="11" collisions="0" teleports="0" halting="19" stopped="4" meanWaitingTime="0.20" meanTravelTime="17.74" meanSpeed="4.96" meanSpeedRelative="0.65" duration="1682727812599"/>
    <step time="225.00" loaded="144" inserted="70" running="58" waiting="0" ended="86" arrived="12" collisions="0" teleports="0" halting="18" stopped="5" meanWaitingTime="0.20" meanTravelTime="18.40" meanSpeed="5.00" meanSpeedRelative="0.60" duration="1682727812674"/>
    <step time="226.00" loaded="144" inserted="70" running="58" waiting="0" ended="86" arrived="12" collisions="0" teleports="0" halting="17" stopped="5" meanWaitingTime="0.20" meanTravelTime="18.40" meanSpeed="5.02" meanSpeedRelative="0.60" duration="1682727812751"/>
    <step time="227.00" loaded="144" inserted="70" running="58" waiting="0" ended="86" arrived="12" collisions="0" teleports="0" halting="17" stopped="5" meanWaitingTime="0.20" meanTravelTime="18.40" meanSpeed="5.01" meanSpeedRelative="0.60" duration="1682727812829"/>
    <step time="228.00" loaded="144" inserted="70" running="58" waiting="0" ended="86" arrived="12" collisions="0" teleports="0" halting="18" stopped="6" meanWaitingTime="0.20" meanTravelTime="18.40" meanSpeed="5.13" meanSpeedRelative="0.59" duration="1682727812904"/>
    <step time="229.00" loaded="144" inserted="70" running="58" waiting="0" ended="86" arrived="12" collisions="0" teleports="0" halting="19" stopped="6" meanWaitingTime="0.20" meanTravelTime="18.40" meanSpeed="5.12" meanSpeedRelative="0.56" duration="1682727812983"/>
    <step time="230.00" loaded="144" inserted="70" running="58" waiting="0" ended="86" arrived="12" collisions="0" teleports="0" halting="21" stopped="7" meanWaitingTime="0.20" meanTravelTime="18.40" meanSpeed="5.35" meanSpeedRelative="0.55" duration="1682727813068"/>
    <step time="231.00" loaded="144" inserted="70" running="58" waiting="0" ended="86" arrived="12" collisions="0" teleports="0" halting="22" stopped="7" meanWaitingTime="0.20" meanTravelTime="18.40" meanSpeed="5.38" meanSpeedRelative="0.55" duration="1682727813146"/>
    <step time="232.00" loaded="144" inserted="70" running="58" waiting="0" ended="86" arrived="12" collisions="0" teleports="0" halting="22" stopped="7" meanWaitingTime="0.20" meanTravelTime="18.40" meanSpeed="5.56" meanSpeedRelative="0.57" duration="1682727813221"/>
    <step time="233.00" loaded="144" inserted="70" running="58" waiting="0" ended="86" arrived="12" collisions="0" teleports="0" halting="22" stopped="7" meanWaitingTime="0.20" meanTravelTime="18.40" meanSpeed="5.69" meanSpeedRelative="0.58" duration="1682727813298"/>
    <step time="234.00" loaded="144" inserted="70" running="57" waiting="0" ended="87" arrived="13" collisions="0" teleports="0" halting="22" stopped="7" meanWaitingTime="0.20" meanTravelTime="20.53" meanSpeed="5.62" meanSpeedRelative="0.58" duration="1682727813477"/>
    <step time="235.00" loaded="146" inserted="70" running="57" waiting="0" ended="89" arrived="13" collisions="0" teleports="0" halting="23" stopped="7" meanWaitingTime="0.20" meanTravelTime="20.07" meanSpeed="5.67" meanSpeedRelative="0.58" duration="1682727813554"/>
    <step time="236.00" loaded="146" inserted="70" running="57" waiting="0" ended="89" arrived="13" collisions="0" teleports="0" halting="23" stopped="7" meanWaitingTime="0.20" meanTravelTime="20.07" meanSpeed="5.68" meanSpeedRelative="0.58" duration="1682727813631"/>
    <step time="237.00" loaded="146" inserted="70" running="57" waiting="0" ended="89" arrived="13" collisions="0" teleports="0" halting="23" stopped="7" meanWaitingTime="0.20" meanTravelTime="20.07" meanSpeed="5.66" meanSpeedRelative="0.58" duration="1682727813715"/>
    <step time="238.00" loaded="146" inserted="70" running="57" waiting="0" ended="89" arrived="13" collisions="0" teleports="0" halting="23" stopped="7" meanWaitingTime="0.20" meanTravelTime="20.07" meanSpeed="5.63" meanSpeedRelative="0.58" duration="1682727813797"/>
    <step time="239.00" loaded="146" inserted="70" running="57" waiting="0" ended="89" arrived="13" collisions="0" teleports="0" halting="23" stopped="7" meanWaitingTime="0.20" meanTravelTime="20.07" meanSpeed="5.67" meanSpeedRelative="0.58" duration="1682727813881"/>
    <step time="240.00" loaded="153" inserted="77" running="64" waiting="0" ended="89" arrived="13" collisions="0" teleports="0" halting="23" stopped="8" meanWaitingTime="0.18" meanTravelTime="20.07" meanSpeed="6.38" meanSpeedRelative="0.61" duration="1682727813971"/>
    <step time="241.00" loaded="155" inserted="77" running="64" waiting="0" ended="91" arrived="13" collisions="0" teleports="0" halting="24" stopped="8" meanWaitingTime="0.18" meanTravelTime="19.63" meanSpeed="6.24" meanSpeedRelative="0.61" duration="1682727814070"/>
    <step time="242.00" loaded="157" inserted="77" running="64" waiting="0" ended="93" arrived="13" collisions="0" teleports="0" halting="24" stopped="8" meanWaitingTime="0.18" meanTravelTime="19.20" meanSpeed="6.15" meanSpeedRelative="0.60" duration="1682727814164"/>
    <step time="243.00" loaded="157" inserted="77" running="63" waiting="0" ended="94" arrived="14" collisions="0" teleports="0" halting="24" stopped="8" meanWaitingTime="0.18" meanTravelTime="20.95" meanSpeed="5.83" meanSpeedRelative="0.57" duration="1682727814256"/>
    <step time="244.00" loaded="157" inserted="77" running="63" waiting="0" ended="94" arrived="14" collisions="0" teleports="0" halting="25" stopped="8" meanWaitingTime="0.18" meanTravelTime="20.95" meanSpeed="5.78" meanSpeedRelative="0.58" duration="1682727814345"/>
    <step time="245.00" loaded="159" inserted="77" running="62" waiting="0" ended="97" arrived="15" collisions="0" teleports="0" halting="24" stopped="8" meanWaitingTime="0.18" meanTravelTime="21.90" meanSpeed="5.70" meanSpeedRelative="0.57" duration="1682727814541"/>
    <step time="246.00" loaded="161" inserted="77" running="62" waiting="0" ended="99" arrived="15" collisions="0" teleports="0" halting="26" stopped="8" meanWaitingTime="0.18" meanTravelTime="21.45" meanSpeed="5.71" meanSpeedRelative="0.58" duration="1682727814624"/>
    <step time="247.00" loaded="163" inserted="77" running="62" waiting="0" ended="101" arrived="15" collisions="0" teleports="0" halting="26" stopped="8" meanWaitingTime="0.18" meanTravelTime="21.03" meanSpeed="5.74" meanSpeedRelative="0.57" duration="1682727814706"/>
    <step time="248.00" loaded="163" inserted="77" running="62" waiting="0" ended="101" arrived="15" collisions="0" teleports="0" halting="26" stopped="8" meanWaitingTime="0.18" meanTravelTime="21.03" meanSpeed="5.66" meanSpeedRelative="0.56" duration="1682727814789"/>
    <step time="249.00" loaded="163" inserted="77" running="62" waiting="0" ended="101" arrived="15" collisions="0" teleports="0" halting="24" stopped="8" meanWaitingTime="0.18" meanTravelTime="21.03" meanSpeed="5.52" meanSpeedRelative="0.55" duration="1682727814869"/>
    <step time="250.00" loaded="163" inserted="77" running="62" waiting="0" ended="101" arrived="15" collisions="0" teleports="0" halting="24" stopped="8" meanWaitingTime="0.18" meanTravelTime="21.03" meanSpeed="5.47" meanSpeedRelative="0.54" duration="1682727814950"/>
    <step time="251.00" loaded="163" inserted="77" running="62" waiting="0" ended="101" arrived="15" collisions="0" teleports="0" halting="24" stopped="8" meanWaitingTime="0.18" meanTravelTime="21.03" meanSpeed="5.57" meanSpeedRelative="0.54" duration="1682727815033"/>
    <step time="252.00" loaded="163" inserted="77" running="62" waiting="0" ended="101" arrived="15" collisions="0" teleports="0" halting="26" stopped="8" meanWaitingTime="0.18" meanTravelTime="21.03" meanSpeed="5.53" meanSpeedRelative="0.52" duration="1682727815114"/>
</summary>
